py_populate_dcim_lib/__init__.py
py_populate_dcim_lib/debug/__init__.py
py_populate_dcim_lib/debug/stand_in_objects.py
py_populate_dcim_lib/fetchers/__init__.py
py_populate_dcim_lib/fetchers/aci/aci_endpoint_vpcs.py
py_populate_dcim_lib/fetchers/aci/aci_helpers.py
py_populate_dcim_lib/fetchers/aci/aci_ip_endpoints.py
py_populate_dcim_lib/fetchers/aci/aci_port_channel.py
py_populate_dcim_lib/fetchers/helpers.py
py_populate_dcim_lib/fetchers/nautobot/device_and_module_types.py
py_populate_dcim_lib/fetchers/nautobot/nautobot.py
py_populate_dcim_lib/fetchers/nautobot/nautobot_helpers.py
py_populate_dcim_lib/fetchers/nautobot/nautobot_virtual_connects.py
py_populate_dcim_lib/fetchers/nautobot/nautobot_vmware_vsphere.py
py_populate_dcim_lib/fetchers/oneview/OneView Synergy LACP Port ID Common Mapping.csv
py_populate_dcim_lib/fetchers/oneview/oneview.py
py_populate_dcim_lib/fetchers/oneview/synergy_virtual_connects.py
py_populate_dcim_lib/fetchers/oneview/vmware_vsphere.py
py_populate_dcim_lib/nautobot-types/device-types/HPE ProLiant DL325 Gen11.yaml
py_populate_dcim_lib/nautobot-types/device-types/HPE ProLiant DL360 Gen10.yaml
py_populate_dcim_lib/nautobot-types/device-types/HPE ProLiant DL380 Gen10 Plus.yaml
py_populate_dcim_lib/nautobot-types/device-types/HPE ProLiant DL380 Gen10.yaml
py_populate_dcim_lib/nautobot-types/device-types/HPE ProLiant DL560 Gen10.yaml
py_populate_dcim_lib/nautobot-types/device-types/HPE Virtual Connect SE 100Gb F32 Module for Synergy.yaml
py_populate_dcim_lib/nautobot-types/device-types/HPE Virtual Connect SE 40Gb F8 Module for Synergy.yaml
py_populate_dcim_lib/nautobot-types/module-types/Broadcom Dual-Port 10 Gb SFP+ Ethernet PCI Express 3.0 x8 OCP3 Mezzanine Card.yaml
py_populate_dcim_lib/nautobot-types/module-types/Broadcom Dual-Port 10Gb Ethernet PCI Express Gen3 x8 NIC.yaml
py_populate_dcim_lib/nautobot-types/module-types/Broadcom P210P - 2 x 10GbE PCIe NIC.yaml
py_populate_dcim_lib-0.1.3.dist-info/METADATA
py_populate_dcim_lib-0.1.3.dist-info/WHEEL
py_populate_dcim_lib-0.1.3.dist-info/RECORD
