Metadata-Version: 2.1
Name: py_populate_dcim_lib
Version: 0.1.3
Summary: A Python tool for fetching, comparing, and displaying hardware addresses with their installation locations. Supports HPE OneView Synergy Frames and Cisco ACI APIC.
Author: Etherflow
Author-email: alan@etherflow.io
Requires-Python: >=3.9,<3.13
Classifier: Programming Language :: Python :: 3
Classifier: Programming Language :: Python :: 3.9
Classifier: Programming Language :: Python :: 3.10
Classifier: Programming Language :: Python :: 3.11
Classifier: Programming Language :: Python :: 3.12
Requires-Dist: etherflow-acitoolkit (>=0.4.5,<0.5.0)
Requires-Dist: hpeoneview (>=9.1.0,<10.0.0)
Requires-Dist: hponeview (>=5.3.0,<6.0.0)
Requires-Dist: pre-commit (>=3.8.0,<4.0.0)
Requires-Dist: pynautobot (>=2.2.1,<3.0.0)
Requires-Dist: python-dotenv (>=1.0.1,<2.0.0)
Requires-Dist: requests-toolbelt (>=1.0.0,<2.0.0)
Requires-Dist: six (>=1.16.0,<2.0.0)
